{"mc":{
	"服":{
		"frameRate":8,
		"labels":[
			{"name":"run","frame":1,"end":9}
			
			],
		"events":[
			
			],
		"frames":[
			
			{
			"res":"Fish_BigClown_Life_01",
			"x":-148,
			"y":-100
			},
			{
			"res":"Fish_BigClown_Life_03",
			"x":-150,
			"y":-106
			},
			{
			"res":"Fish_BigClown_Life_05",
			"x":-146,
			"y":-111
			},
			{
			"res":"Fish_BigClown_Life_07",
			"x":-145,
			"y":-110
			},
			{
			"res":"Fish_BigClown_Life_09",
			"x":-149,
			"y":-118
			},
			{
			"res":"Fish_BigClown_Life_11",
			"x":-149,
			"y":-114
			},
			{
			"res":"Fish_BigClown_Life_13",
			"x":-145,
			"y":-99
			},
			{
			"res":"Fish_BigClown_Life_14",
			"x":-144,
			"y":-95
			},
			{
			"res":"Fish_BigClown_Life_15",
			"x":-146,
			"y":-97
			}
			]
}},
	"res":{
		"Fish_BigClown_Life_13":{"x":300,"y":442,"w":293,"h":202},
		"Fish_BigClown_Life_07":{"x":598,"y":229,"w":293,"h":225},
		"Fish_BigClown_Life_09":{"x":0,"y":0,"w":297,"h":242},
		"Fish_BigClown_Life_11":{"x":299,"y":0,"w":297,"h":234},
		"Fish_BigClown_Life_01":{"x":300,"y":236,"w":296,"h":204},
		"Fish_BigClown_Life_03":{"x":0,"y":244,"w":298,"h":217},
		"Fish_BigClown_Life_15":{"x":0,"y":463,"w":294,"h":199},
		"Fish_BigClown_Life_05":{"x":598,"y":0,"w":294,"h":227},
		"Fish_BigClown_Life_14":{"x":595,"y":456,"w":292,"h":194}
	}}