{"mc":{
	"fish_17":{
		"frameRate":8,
		"labels":[
			{"name":"run","frame":1,"end":17}
			
			],
		"events":[
			
			],
		"frames":[
			
			{
			"res":"Fish_BossCrocodile_Life_001",
			"x":-276,
			"y":-84
			},
			{
			"res":"Fish_BossCrocodile_Life_002",
			"x":-283,
			"y":-86
			},
			{
			"res":"Fish_BossCrocodile_Life_003",
			"x":-289,
			"y":-87
			},
			{
			"res":"Fish_BossCrocodile_Life_004",
			"x":-290,
			"y":-86
			},
			{
			"res":"Fish_BossCrocodile_Life_005",
			"x":-285,
			"y":-95
			},
			{
			"res":"Fish_BossCrocodile_Life_006",
			"x":-282,
			"y":-100
			},
			{
			"res":"Fish_BossCrocodile_Life_007",
			"x":-274,
			"y":-108
			},
			{
			"res":"Fish_BossCrocodile_Life_008",
			"x":-270,
			"y":-104
			},
			{
			"res":"Fish_BossCrocodile_Life_009",
			"x":-271,
			"y":-86
			},
			{
			"res":"Fish_BossCrocodile_Life_010",
			"x":-278,
			"y":-77
			},
			{
			"res":"Fish_BossCrocodile_Life_011",
			"x":-282,
			"y":-78
			},
			{
			"res":"Fish_BossCrocodile_Life_012",
			"x":-289,
			"y":-77
			},
			{
			"res":"Fish_BossCrocodile_Life_013",
			"x":-291,
			"y":-76
			},
			{
			"res":"Fish_BossCrocodile_Life_014",
			"x":-287,
			"y":-75
			},
			{
			"res":"Fish_BossCrocodile_Life_015",
			"x":-278,
			"y":-74
			},
			{
			"res":"Fish_BossCrocodile_Life_016",
			"x":-275,
			"y":-76
			},
			{
			"res":"Fish_BossCrocodile_Life_017",
			"x":-272,
			"y":-80
			}
			]
}},
	"res":{
		"Fish_BossCrocodile_Life_007":{"x":0,"y":0,"w":534,"h":195},
		"Fish_BossCrocodile_Life_001":{"x":0,"y":936,"w":536,"h":175},
		"Fish_BossCrocodile_Life_004":{"x":544,"y":375,"w":550,"h":178},
		"Fish_BossCrocodile_Life_003":{"x":1083,"y":0,"w":549,"h":180},
		"Fish_BossCrocodile_Life_012":{"x":1096,"y":373,"w":549,"h":175},
		"Fish_BossCrocodile_Life_008":{"x":0,"y":197,"w":530,"h":194},
		"Fish_BossCrocodile_Life_006":{"x":0,"y":393,"w":542,"h":189},
		"Fish_BossCrocodile_Life_002":{"x":1073,"y":555,"w":543,"h":178},
		"Fish_BossCrocodile_Life_015":{"x":1073,"y":187,"w":538,"h":184},
		"Fish_BossCrocodile_Life_011":{"x":551,"y":917,"w":542,"h":176},
		"Fish_BossCrocodile_Life_009":{"x":553,"y":735,"w":531,"h":180},
		"Fish_BossCrocodile_Life_005":{"x":536,"y":0,"w":545,"h":185},
		"Fish_BossCrocodile_Life_016":{"x":536,"y":187,"w":535,"h":186},
		"Fish_BossCrocodile_Life_017":{"x":1086,"y":735,"w":532,"h":179},
		"Fish_BossCrocodile_Life_013":{"x":0,"y":584,"w":551,"h":174},
		"Fish_BossCrocodile_Life_014":{"x":0,"y":760,"w":549,"h":174},
		"Fish_BossCrocodile_Life_010":{"x":1095,"y":916,"w":538,"h":174}
	}}