{
  "file": "buyu_selectScene.png",
  "frames": {
    "by_title_hk_png": {
      "x": 355,
      "y": 499,
      "w": 253,
      "h": 85,
      "offX": 33,
      "offY": 4,
      "sourceW": 309,
      "sourceH": 90
    },
    "hwpy_room_dikuang_png": {
      "x": 710,
      "y": 0,
      "w": 193,
      "h": 183,
      "offX": 0,
      "offY": 0,
      "sourceW": 193,
      "sourceH": 183
    },
    "lobby_experience_icon_png": {
      "x": 802,
      "y": 237,
      "w": 48,
      "h": 47,
      "offX": 0,
      "offY": 3,
      "sourceW": 48,
      "sourceH": 50
    },
    "lobby_gold_icon_png": {
      "x": 880,
      "y": 185,
      "w": 48,
      "h": 47,
      "offX": 0,
      "offY": 3,
      "sourceW": 48,
      "sourceH": 50
    },
    "py_addexperience_btn_png": {
      "x": 710,
      "y": 328,
      "w": 60,
      "h": 50,
      "offX": 0,
      "offY": 7,
      "sourceW": 60,
      "sourceH": 57
    },
    "py_addexperience_downbtn_png": {
      "x": 710,
      "y": 328,
      "w": 60,
      "h": 50,
      "offX": 0,
      "offY": 7,
      "sourceW": 60,
      "sourceH": 57
    },
    "py_coin_bg": {
      "x": 0,
      "y": 959,
      "w": 177,
      "h": 41,
      "offX": 0,
      "offY": 0,
      "sourceW": 177,
      "sourceH": 41
    },
    "py_experience_png": {
      "x": 0,
      "y": 0,
      "w": 353,
      "h": 385,
      "offX": 0,
      "offY": 0,
      "sourceW": 353,
      "sourceH": 386
    },
    "py_help": {
      "x": 355,
      "y": 638,
      "w": 82,
      "h": 84,
      "offX": 0,
      "offY": 0,
      "sourceW": 82,
      "sourceH": 84
    },
    "py_machine_soonBtnDown_png": {
      "x": 355,
      "y": 387,
      "w": 290,
      "h": 110,
      "offX": 0,
      "offY": 0,
      "sourceW": 290,
      "sourceH": 110
    },
    "py_machine_soonBtnNormal_png": {
      "x": 355,
      "y": 387,
      "w": 290,
      "h": 110,
      "offX": 0,
      "offY": 0,
      "sourceW": 290,
      "sourceH": 110
    },
    "py_name_bg": {
      "x": 647,
      "y": 387,
      "w": 177,
      "h": 32,
      "offX": 0,
      "offY": 0,
      "sourceW": 177,
      "sourceH": 32
    },
    "py_select_btnDown_png": {
      "x": 905,
      "y": 91,
      "w": 82,
      "h": 84,
      "offX": 0,
      "offY": 0,
      "sourceW": 82,
      "sourceH": 84
    },
    "py_select_btnNormal_png": {
      "x": 905,
      "y": 91,
      "w": 82,
      "h": 84,
      "offX": 0,
      "offY": 0,
      "sourceW": 82,
      "sourceH": 84
    },
    "py_select_headBg_png": {
      "x": 905,
      "y": 0,
      "w": 90,
      "h": 89,
      "offX": 0,
      "offY": 0,
      "sourceW": 90,
      "sourceH": 89
    },
    "py_select_headMask_png": {
      "x": 710,
      "y": 237,
      "w": 90,
      "h": 89,
      "offX": 0,
      "offY": 0,
      "sourceW": 90,
      "sourceH": 89
    },
    "py_select_icon_png": {
      "x": 0,
      "y": 774,
      "w": 309,
      "h": 90,
      "offX": 0,
      "offY": 0,
      "sourceW": 309,
      "sourceH": 90
    },
    "py_title_level1_png": {
      "x": 710,
      "y": 185,
      "w": 168,
      "h": 50,
      "offX": 0,
      "offY": 0,
      "sourceW": 168,
      "sourceH": 50
    },
    "py_title_level2_png": {
      "x": 0,
      "y": 907,
      "w": 168,
      "h": 50,
      "offX": 0,
      "offY": 0,
      "sourceW": 168,
      "sourceH": 50
    },
    "py_title_level3_png": {
      "x": 355,
      "y": 586,
      "w": 168,
      "h": 50,
      "offX": 0,
      "offY": 0,
      "sourceW": 168,
      "sourceH": 50
    },
    "py_worldNew_bg": {
      "x": 0,
      "y": 866,
      "w": 695,
      "h": 39,
      "offX": 0,
      "offY": 0,
      "sourceW": 695,
      "sourceH": 39
    },
    "py_yqs_diamond_png": {
      "x": 355,
      "y": 0,
      "w": 353,
      "h": 385,
      "offX": 0,
      "offY": 1,
      "sourceW": 353,
      "sourceH": 386
    },
    "py_yqs_platinum_png": {
      "x": 0,
      "y": 387,
      "w": 353,
      "h": 385,
      "offX": 0,
      "offY": 1,
      "sourceW": 353,
      "sourceH": 386
    }
  }
}